Changelog.rst
Developer_Manual.rst
LICENSE.txt
MANIFEST.in
README.rst
pyproject.toml
setup.cfg
setup.py
BLooDNiNjA/Builtins.py
BLooDNiNjA/BytecodeCaching.py
BLooDNiNjA/Bytecodes.py
BLooDNiNjA/CacheCleanup.py
BLooDNiNjA/Constants.py
BLooDNiNjA/Errors.py
BLooDNiNjA/HardImportRegistry.py
BLooDNiNjA/MainControl.py
BLooDNiNjA/ModuleRegistry.py
BLooDNiNjA/OptionParsing.py
BLooDNiNjA/Options.py
BLooDNiNjA/OutputDirectories.py
BLooDNiNjA/PostProcessing.py
BLooDNiNjA/Progress.py
BLooDNiNjA/PythonFlavors.py
BLooDNiNjA/PythonOperators.py
BLooDNiNjA/PythonVersions.py
BLooDNiNjA/Serialization.py
BLooDNiNjA/SourceCodeReferences.py
BLooDNiNjA/Tracing.py
BLooDNiNjA/TreeXML.py
BLooDNiNjA/Variables.py
BLooDNiNjA/Version.py
BLooDNiNjA/__init__.py
BLooDNiNjA/__main__.py
BLooDNiNjA/__past__.py
BLooDNiNjA/build/Backend.scons
BLooDNiNjA/build/CCompilerVersion.scons
BLooDNiNjA/build/DataComposerInterface.py
BLooDNiNjA/build/Offsets.scons
BLooDNiNjA/build/Onefile.scons
BLooDNiNjA/build/SconsCaching.py
BLooDNiNjA/build/SconsCompilerSettings.py
BLooDNiNjA/build/SconsHacks.py
BLooDNiNjA/build/SconsInterface.py
BLooDNiNjA/build/SconsProgress.py
BLooDNiNjA/build/SconsSpawn.py
BLooDNiNjA/build/SconsUtils.py
BLooDNiNjA/build/__init__.py
BLooDNiNjA/build/include/BLooDNiNjA/allocator.h
BLooDNiNjA/build/include/BLooDNiNjA/builtins.h
BLooDNiNjA/build/include/BLooDNiNjA/calling.h
BLooDNiNjA/build/include/BLooDNiNjA/checkers.h
BLooDNiNjA/build/include/BLooDNiNjA/checksum_tools.h
BLooDNiNjA/build/include/BLooDNiNjA/compiled_asyncgen.h
BLooDNiNjA/build/include/BLooDNiNjA/compiled_cell.h
BLooDNiNjA/build/include/BLooDNiNjA/compiled_coroutine.h
BLooDNiNjA/build/include/BLooDNiNjA/compiled_frame.h
BLooDNiNjA/build/include/BLooDNiNjA/compiled_function.h
BLooDNiNjA/build/include/BLooDNiNjA/compiled_generator.h
BLooDNiNjA/build/include/BLooDNiNjA/compiled_method.h
BLooDNiNjA/build/include/BLooDNiNjA/constants.h
BLooDNiNjA/build/include/BLooDNiNjA/constants_blob.h
BloodQ.egg-info/PKG-INFO
BloodQ.egg-info/SOURCES.txt
BloodQ.egg-info/dependency_links.txt
BloodQ.egg-info/entry_points.txt
BloodQ.egg-info/not-zip-safe
BloodQ.egg-info/requires.txt
BloodQ.egg-info/top_level.txt
